functor_ninja/__init__.py
functor_ninja/list_monad.py
functor_ninja/monad.py
functor_ninja/retry_monad.py
functor_ninja/test_list.py
functor_ninja/test_retry.py
functor_ninja/test_try.py
functor_ninja/try_monad.py
functor_ninja-0.4.0.dist-info/METADATA
functor_ninja-0.4.0.dist-info/WHEEL
functor_ninja-0.4.0.dist-info/RECORD
