Metadata-Version: 2.3
Name: functor-ninja
Version: 0.4.0
Summary: Functors and Monads for data processing
Author: Felipe Ortega
Author-email: felipeortegabustamante@gmail.com
Requires-Python: >=3.9,<4.0
Classifier: Programming Language :: Python :: 3
Classifier: Programming Language :: Python :: 3.9
Classifier: Programming Language :: Python :: 3.10
Classifier: Programming Language :: Python :: 3.11
Classifier: Programming Language :: Python :: 3.12
Classifier: Programming Language :: Python :: 3.13
